appdynamics_bindeps/__init__.py
appdynamics_bindeps/google/__init__.py
appdynamics_bindeps/google/protobuf/__init__.py
appdynamics_bindeps/google/protobuf/any_pb2.py
appdynamics_bindeps/google/protobuf/any_test_pb2.py
appdynamics_bindeps/google/protobuf/api_pb2.py
appdynamics_bindeps/google/protobuf/descriptor.py
appdynamics_bindeps/google/protobuf/descriptor_database.py
appdynamics_bindeps/google/protobuf/descriptor_pb2.py
appdynamics_bindeps/google/protobuf/descriptor_pool.py
appdynamics_bindeps/google/protobuf/duration_pb2.py
appdynamics_bindeps/google/protobuf/empty_pb2.py
appdynamics_bindeps/google/protobuf/field_mask_pb2.py
appdynamics_bindeps/google/protobuf/json_format.py
appdynamics_bindeps/google/protobuf/map_unittest_pb2.py
appdynamics_bindeps/google/protobuf/message.py
appdynamics_bindeps/google/protobuf/message_factory.py
appdynamics_bindeps/google/protobuf/proto_builder.py
appdynamics_bindeps/google/protobuf/reflection.py
appdynamics_bindeps/google/protobuf/service.py
appdynamics_bindeps/google/protobuf/service_reflection.py
appdynamics_bindeps/google/protobuf/source_context_pb2.py
appdynamics_bindeps/google/protobuf/struct_pb2.py
appdynamics_bindeps/google/protobuf/symbol_database.py
appdynamics_bindeps/google/protobuf/text_encoding.py
appdynamics_bindeps/google/protobuf/text_format.py
appdynamics_bindeps/google/protobuf/timestamp_pb2.py
appdynamics_bindeps/google/protobuf/type_pb2.py
appdynamics_bindeps/google/protobuf/unittest_arena_pb2.py
appdynamics_bindeps/google/protobuf/unittest_custom_options_pb2.py
appdynamics_bindeps/google/protobuf/unittest_import_pb2.py
appdynamics_bindeps/google/protobuf/unittest_import_public_pb2.py
appdynamics_bindeps/google/protobuf/unittest_mset_pb2.py
appdynamics_bindeps/google/protobuf/unittest_mset_wire_format_pb2.py
appdynamics_bindeps/google/protobuf/unittest_no_arena_import_pb2.py
appdynamics_bindeps/google/protobuf/unittest_no_arena_pb2.py
appdynamics_bindeps_osx_x64-11.0.dist-info/DESCRIPTION.rst
appdynamics_bindeps_osx_x64-11.0.dist-info/METADATA
appdynamics_bindeps_osx_x64-11.0.dist-info/RECORD
appdynamics_bindeps_osx_x64-11.0.dist-info/WHEEL
appdynamics_bindeps_osx_x64-11.0.dist-info/metadata.json
appdynamics_bindeps_osx_x64-11.0.dist-info/top_level.txt
