Metadata-Version: 2.0
Name: appdynamics-bindeps-osx-x64
Version: 11.0
Summary: Dependencies for AppDynamics Python agent
Home-page: http://www.appdynamics.com
Author: AppDynamics
Author-email: support@appdynamics.com
License: Proprietary
Platform: UNKNOWN
